conomy_data_client/__init__.py
conomy_data_client-0.0.1.dist-info/LICENSE
conomy_data_client-0.0.1.dist-info/METADATA
conomy_data_client-0.0.1.dist-info/WHEEL
conomy_data_client-0.0.1.dist-info/top_level.txt
conomy_data_client-0.0.1.dist-info/RECORD
