Metadata-Version: 2.1
Name: conomy-data-client
Version: 0.0.1
Summary: Cliet for access to "Conomy Data" microservice
Home-page: https://github.com/soogly/conomy-data-client.git
Author: Andrey Suglobov
Author-email: suglobov@conomy.ru
License: UNKNOWN
Platform: UNKNOWN
Classifier: Programming Language :: Python :: 3
Classifier: License :: OSI Approved :: MIT License
Classifier: Operating System :: OS Independent
Requires-Python: >=3.6
